paddle3d/__init__.py
paddle3d/env.py
paddle3d/sample.py
paddle3d/apis/__init__.py
paddle3d/apis/checkpoint.py
paddle3d/apis/config.py
paddle3d/apis/manager.py
paddle3d/apis/pipeline.py
paddle3d/apis/scheduler.py
paddle3d/apis/trainer.py
paddle3d/datasets/__init__.py
paddle3d/datasets/base.py
paddle3d/datasets/generate_gt_database.py
paddle3d/datasets/metrics.py
paddle3d/datasets/kitti/__init__.py
paddle3d/datasets/kitti/kitti_depth_det.py
paddle3d/datasets/kitti/kitti_det.py
paddle3d/datasets/kitti/kitti_metric.py
paddle3d/datasets/kitti/kitti_mono_det.py
paddle3d/datasets/kitti/kitti_pointcloud_det.py
paddle3d/datasets/kitti/kitti_utils.py
paddle3d/datasets/modelnet40/__init__.py
paddle3d/datasets/modelnet40/modelnet40_cls.py
paddle3d/datasets/modelnet40/modelnet40_metric.py
paddle3d/datasets/nuscenes/__init__.py
paddle3d/datasets/nuscenes/nuscenes_det.py
paddle3d/datasets/nuscenes/nuscenes_manager.py
paddle3d/datasets/nuscenes/nuscenes_metric.py
paddle3d/datasets/nuscenes/nuscenes_multiview_det.py
paddle3d/datasets/nuscenes/nuscenes_pointcloud_det.py
paddle3d/datasets/nuscenes/nuscenes_utils.py
paddle3d/datasets/semantic_kitti/__init__.py
paddle3d/datasets/semantic_kitti/semantic_kitti.py
paddle3d/datasets/semantic_kitti/semantic_kitti_metric.py
paddle3d/datasets/semantic_kitti/semantic_kitti_seg.py
paddle3d/datasets/waymo/__init__.py
paddle3d/datasets/waymo/waymo_det.py
paddle3d/datasets/waymo/waymo_metric.py
paddle3d/datasets/waymo/waymo_pointcloud_det.py
paddle3d/datasets/waymo/waymo_utils.py
paddle3d/geometries/__init__.py
paddle3d/geometries/bbox.py
paddle3d/geometries/pointcloud.py
paddle3d/geometries/structure.py
paddle3d/models/__init__.py
paddle3d/models/backbones/__init__.py
paddle3d/models/backbones/dla.py
paddle3d/models/backbones/hrnet.py
paddle3d/models/backbones/resnet.py
paddle3d/models/backbones/sac.py
paddle3d/models/backbones/second_backbone.py
paddle3d/models/backbones/vovnet.py
paddle3d/models/backbones/vovnetcp.py
paddle3d-1.0.0.dist-info/LICENSE
paddle3d-1.0.0.dist-info/METADATA
paddle3d-1.0.0.dist-info/WHEEL
paddle3d-1.0.0.dist-info/top_level.txt
paddle3d-1.0.0.dist-info/RECORD
