Metadata-Version: 2.1
Name: paddle3d
Version: 1.0.0
Home-page: https://github.com/PaddlePaddle/Paddle3D
Author: PaddlePaddle Author
Author-email: 
License: Apache 2.0
Keywords: paddle3d paddlepaddle pointcloud detection classification segmentation
Classifier: Development Status :: 3 - Alpha
Classifier: Intended Audience :: Developers
Classifier: Intended Audience :: Education
Classifier: Intended Audience :: Science/Research
Classifier: License :: OSI Approved :: Apache Software License
Classifier: Programming Language :: Python :: 3.6
Classifier: Programming Language :: Python :: 3.7
Classifier: Programming Language :: Python :: 3.8
Classifier: Topic :: Scientific/Engineering
Classifier: Topic :: Scientific/Engineering :: Mathematics
Classifier: Topic :: Scientific/Engineering :: Artificial Intelligence
Classifier: Topic :: Software Development
Classifier: Topic :: Software Development :: Libraries
Classifier: Topic :: Software Development :: Libraries :: Python Modules
License-File: LICENSE
Requires-Dist: colorlog
Requires-Dist: easydict
Requires-Dist: filelock
Requires-Dist: numba (>=0.56)
Requires-Dist: numpy
Requires-Dist: nuscenes-devkit
Requires-Dist: opencv-python
Requires-Dist: pandas
Requires-Dist: paddledet
Requires-Dist: paddleseg
Requires-Dist: pyquaternion
Requires-Dist: pyyaml
Requires-Dist: pillow (<=8.3.2)
Requires-Dist: rarfile
Requires-Dist: scikit-image
Requires-Dist: scikit-learn
Requires-Dist: visualdl
Requires-Dist: h5py
